{
    "name": "Articulo",
    "fields": [
        {
            "fieldName": "codigo",
            "fieldType": "String"
        },
        {
            "fieldName": "descripcion",
            "fieldType": "String"
        },
        {
            "fieldName": "ubicacion",
            "fieldType": "String"
        },
        {
            "fieldName": "unidad",
            "fieldType": "String"
        },
        {
            "fieldName": "valorUnidad",
            "fieldType": "Integer"
        },
        {
            "fieldName": "idProveedor",
            "fieldType": "String"
        }
    ],
    "relationships": [
        {
            "relationshipName": "proveedor",
            "otherEntityName": "proveedor",
            "relationshipType": "many-to-one",
            "otherEntityField": "id"
        }
    ],
    "changelogDate": "20190222031618",
    "entityTableName": "articulo",
    "dto": "no",
    "pagination": "pagination",
    "service": "no",
    "jpaMetamodelFiltering": false,
    "fluentMethods": true,
    "clientRootFolder": "",
    "applications": "*"
}